LICENSE
MANIFEST.in
README.md
setup.cfg
setup.py
django_pycharm_debug_middleware.egg-info/PKG-INFO
django_pycharm_debug_middleware.egg-info/SOURCES.txt
django_pycharm_debug_middleware.egg-info/dependency_links.txt
django_pycharm_debug_middleware.egg-info/not-zip-safe
django_pycharm_debug_middleware.egg-info/requires.txt
django_pycharm_debug_middleware.egg-info/top_level.txt
pycharm_debug_middleware/__init__.py
pycharm_debug_middleware/middleware.py